{
  "profile_id": "P10",
  "persona": {
    "demographics": null,
    "personality_traits": [
      "self-critical",
      "emotionally reactive"
    ],
    "core_values": [],
    "core_beliefs": [],
    "support_system": "friend from thrift store, possibly fragile, and no other mentioned support",
    "hobbies_interests": [
      "baking"
    ],
    "communication_style": "emotional, reflective",
    "relevant_history": "lost job at bakery, struggling with rent, received eviction notice, experiencing stomach pain, car is broken",
    "general_behavioral_traits": [
      "overthinker",
      "emotionally reactive",
      "self-critical",
      "anxious",
      "avoidant"
    ]
  },
  "problems": {},
  "edges": []
}